licit/__init__.py
licit-0.1.0.dist-info/LICENSE
licit-0.1.0.dist-info/METADATA
licit-0.1.0.dist-info/WHEEL
licit-0.1.0.dist-info/RECORD
