Metadata-Version: 2.1
Name: licit
Version: 0.1.0
Summary: Check if a license is compatible with its dependencies
License: AGPL-3.0
Author: sneakers-the-rat
Author-email: j@nny.fyi
Requires-Python: >=3.11,<4.0
Classifier: License :: OSI Approved :: GNU Affero General Public License v3
Classifier: Programming Language :: Python :: 3
Classifier: Programming Language :: Python :: 3.11
